Metadata-Version: 1.0
Name: elkdist
Version: 1.0
Summary: Probability distributions
Home-page: UNKNOWN
Author: Adham El-Khouly
Author-email: UNKNOWN
License: UNKNOWN
Platform: UNKNOWN
